2017B4A70849P.v
// ID: 2017B4A70849P
// Name:V.Aravindan

module RSFF(Q,S,R,clk,reset);
  input S,R,clk,reset;
  output reg Q;
  always@(posedge clk)
    begin
      case({S,R})
        2'b01: Q=1'b0;
        2'b10: Q=1'b1;
        2'b11: Q=1'b1;
      endcase
    end
  always@(reset)
      begin
        if(reset)
          Q=0;
      end
endmodule

module DFF(Q,D,clk,reset);
input D,clk,reset;
output Q;
wire nd;
assign nd=~D;
RSFF rsff(Q,D,nd,clk,reset);
endmodule

module Ripple_Counter(Q,clk,reset);
input clk,reset;
output [3:0]Q;
DFF FF0(Q[0],~Q[0],clk,reset);
DFF FF1(Q[1],~Q[1],~Q[0],reset);
DFF FF2(Q[2],~Q[2],~Q[1],reset);
DFF FF3(Q[3],~Q[3],~Q[2],reset);
endmodule

module MEM1(Data,Parity,Addr);
input [2:0]Addr;
output reg [7:0]Data;
output reg Parity;
reg [8:0]memory[0:7];
initial
  begin
    memory[0]=9'b0001_1111_1;
    memory[1]=9'b0011_0001_1;
    memory[2]=9'b0101_0011_1;
    memory[3]=9'b0111_0101_1;
    memory[4]=9'b1001_0111_1;
    memory[5]=9'b1011_1001_1;
    memory[6]=9'b1101_1011_1;
    memory[7]=9'b1111_1101_1;
  end
always@(Addr)
  begin
    Parity=1'b1;
    case(Addr)
      3'd0:Data=memory[0][8:1];
      3'd1:Data=memory[1][8:1];
      3'd2:Data=memory[2][8:1];
      3'd3:Data=memory[3][8:1];
      3'd4:Data=memory[4][8:1];
      3'd5:Data=memory[5][8:1];
      3'd6:Data=memory[6][8:1];
      3'd7:Data=memory[7][8:1];
    endcase
  end
endmodule

module MEM2(Data,Parity,Addr);
input [2:0]Addr;
output reg [7:0]Data;
output reg Parity;
reg [8:0]memory[0:7];
initial
  begin
    memory[0]=9'b0000_0000_0;
    memory[1]=9'b0010_0010_0;
    memory[2]=9'b0100_0100_0;
    memory[3]=9'b0110_0110_0;
    memory[4]=9'b1000_1000_0;
    memory[5]=9'b1010_1010_0;
    memory[6]=9'b1100_1100_0;
    memory[7]=9'b1110_1110_0;
  end
always@(Addr)
  begin
    Parity=1'b0;
    case(Addr)
      3'd0:Data=memory[0][8:1];
      3'd1:Data=memory[1][8:1];
      3'd2:Data=memory[2][8:1];
      3'd3:Data=memory[3][8:1];
      3'd4:Data=memory[4][8:1];
      3'd5:Data=memory[5][8:1];
      3'd6:Data=memory[6][8:1];
      3'd7:Data=memory[7][8:1];
    endcase
  end
endmodule

module MUX2To1(out,in,sel);
input [1:0]in;
input sel;
output out;
assign out=(sel)?in[1]:in[0];
endmodule

module MUX16To8(out,in1,in2,sel);
input [7:0]in1,in2;
input sel;
output [7:0]out;
genvar i;
generate
for(i=0;i<8;i=i+1) begin:mux_loop
   MUX2To1 m(out[i],{in2[i],in1[i]},sel);
  end
endgenerate
endmodule

module Fetch_Data(Data,Parity,Addr);
input [3:0]Addr;
wire [7:0]Data1,Data2;
wire Parity1,Parity2;
output [7:0]Data;
output Parity;
MEM1 m1(Data1,Parity1,Addr[2:0]);
MEM2 m2(Data2,Parity2,Addr[2:0]);
MUX2To1 parity_mux(Parity,{Parity2,Parity1},Addr[3]);
MUX16To8 data_mux(Data,Data1,Data2,Addr[3]);
endmodule

module Parity_Checker(Match_result,Data,Parity);
input [7:0]Data;
input Parity;
output Match_result;
wire Data_Parity;
assign Data_Parity=Data[0]+Data[1]+Data[2]+Data[3]+Data[4]+Data[5]+Data[6]+Data[7];
assign Match_result=~(Parity^Data_Parity);
endmodule

module Design(out,clk,reset);
input clk,reset;
output out;
wire [3:0]Addr;
wire [7:0]Data_fetched;
wire Parity_fetched;
Ripple_Counter rc(Addr,clk,reset);
Fetch_Data fd(Data_fetched, Parity_fetched, Addr);
Parity_Checker pc(out,Data_fetched,Parity_fetched);
endmodule

module TestBench;
initial
  begin
    $dumpfile("2017B4A70849P.vcd");
    $dumpvars;
  end
reg clk,reset;
wire out;
Design d(out,clk,reset);
initial
  begin
    clk=1'b0; reset=1'b1;
    #1 reset=1'b0;
    #100 $finish;
  end
always
   #0.5 clk=~clk;
initial
    $monitor($time,"   clk=%b reset=%b |||||| output=%b ",clk,,reset,out);
endmodule

2017B4A70849P.vcd
$date
	Mon Nov 09 06:16:54 2020
$end
$version
	Icarus Verilog
$end
$timescale
	1s
$end
$scope module TestBench $end
$var wire 1 ! out $end
$var reg 1 " clk $end
$var reg 1 # reset $end
$scope module d $end
$var wire 1 " clk $end
$var wire 1 # reset $end
$var wire 1 ! out $end
$var wire 1 $ Parity_fetched $end
$var wire 8 % Data_fetched [7:0] $end
$var wire 4 & Addr [3:0] $end
$scope module fd $end
$var wire 1 ' Parity2 $end
$var wire 1 ( Parity1 $end
$var wire 1 $ Parity $end
$var wire 8 ) Data2 [7:0] $end
$var wire 8 * Data1 [7:0] $end
$var wire 8 + Data [7:0] $end
$var wire 4 , Addr [3:0] $end
$scope module data_mux $end
$var wire 1 - sel $end
$var wire 8 . out [7:0] $end
$var wire 8 / in2 [7:0] $end
$var wire 8 0 in1 [7:0] $end
$scope begin mux_loop[0] $end
$scope module m $end
$var wire 2 1 in [1:0] $end
$var wire 1 - sel $end
$var wire 1 2 out $end
$upscope $end
$upscope $end
$scope begin mux_loop[1] $end
$scope module m $end
$var wire 2 3 in [1:0] $end
$var wire 1 - sel $end
$var wire 1 4 out $end
$upscope $end
$upscope $end
$scope begin mux_loop[2] $end
$scope module m $end
$var wire 2 5 in [1:0] $end
$var wire 1 - sel $end
$var wire 1 6 out $end
$upscope $end
$upscope $end
$scope begin mux_loop[3] $end
$scope module m $end
$var wire 2 7 in [1:0] $end
$var wire 1 - sel $end
$var wire 1 8 out $end
$upscope $end
$upscope $end
$scope begin mux_loop[4] $end
$scope module m $end
$var wire 2 9 in [1:0] $end
$var wire 1 - sel $end
$var wire 1 : out $end
$upscope $end
$upscope $end
$scope begin mux_loop[5] $end
$scope module m $end
$var wire 2 ; in [1:0] $end
$var wire 1 - sel $end
$var wire 1 < out $end
$upscope $end
$upscope $end
$scope begin mux_loop[6] $end
$scope module m $end
$var wire 2 = in [1:0] $end
$var wire 1 - sel $end
$var wire 1 > out $end
$upscope $end
$upscope $end
$scope begin mux_loop[7] $end
$scope module m $end
$var wire 2 ? in [1:0] $end
$var wire 1 - sel $end
$var wire 1 @ out $end
$upscope $end
$upscope $end
$upscope $end
$scope module m1 $end
$var wire 3 A Addr [2:0] $end
$var reg 8 B Data [7:0] $end
$var reg 1 ( Parity $end
$upscope $end
$scope module m2 $end
$var wire 3 C Addr [2:0] $end
$var reg 8 D Data [7:0] $end
$var reg 1 ' Parity $end
$upscope $end
$scope module parity_mux $end
$var wire 2 E in [1:0] $end
$var wire 1 F sel $end
$var wire 1 $ out $end
$upscope $end
$upscope $end
$scope module pc $end
$var wire 8 G Data [7:0] $end
$var wire 1 ! Match_result $end
$var wire 1 $ Parity $end
$var wire 1 H Data_Parity $end
$upscope $end
$scope module rc $end
$var wire 1 " clk $end
$var wire 1 # reset $end
$var wire 4 I Q [3:0] $end
$scope module FF0 $end
$var wire 1 J D $end
$var wire 1 " clk $end
$var wire 1 K nd $end
$var wire 1 # reset $end
$var wire 1 L Q $end
$scope module rsff $end
$var wire 1 K R $end
$var wire 1 J S $end
$var wire 1 " clk $end
$var wire 1 # reset $end
$var reg 1 L Q $end
$upscope $end
$upscope $end
$scope module FF1 $end
$var wire 1 M D $end
$var wire 1 N clk $end
$var wire 1 O nd $end
$var wire 1 # reset $end
$var wire 1 P Q $end
$scope module rsff $end
$var wire 1 O R $end
$var wire 1 M S $end
$var wire 1 N clk $end
$var wire 1 # reset $end
$var reg 1 P Q $end
$upscope $end
$upscope $end
$scope module FF2 $end
$var wire 1 Q D $end
$var wire 1 R clk $end
$var wire 1 S nd $end
$var wire 1 # reset $end
$var wire 1 T Q $end
$scope module rsff $end
$var wire 1 S R $end
$var wire 1 Q S $end
$var wire 1 R clk $end
$var wire 1 # reset $end
$var reg 1 T Q $end
$upscope $end
$upscope $end
$scope module FF3 $end
$var wire 1 U D $end
$var wire 1 V clk $end
$var wire 1 W nd $end
$var wire 1 # reset $end
$var wire 1 X Q $end
$scope module rsff $end
$var wire 1 W R $end
$var wire 1 U S $end
$var wire 1 V clk $end
$var wire 1 # reset $end
$var reg 1 X Q $end
$upscope $end
$upscope $end
$upscope $end
$upscope $end
$upscope $end
$enddefinitions $end
#0
$dumpvars
0X
0W
1V
1U
0T
0S
1R
1Q
0P
0O
1N
1M
0L
0K
1J
b0 I
1H
b11111 G
0F
b1 E
b0 D
b0 C
b11111 B
b0 A
0@
b0 ?
0>
b0 =
0<
b0 ;
1:
b1 9
18
b1 7
16
b1 5
14
b1 3
12
b1 1
b11111 0
b0 /
b11111 .
0-
b0 ,
b11111 +
b11111 *
b0 )
1(
0'
b0 &
b11111 %
1$
1#
0"
1!
$end
#1
1H
1<
08
06
b110001 %
b110001 +
b110001 .
b110001 G
04
1K
b11 ;
b0 7
b0 5
b10 3
0N
0J
b100010 )
b100010 /
b100010 D
b110001 *
b110001 0
b110001 B
b1 C
b1 A
b1 &
b1 ,
b1 I
1L
1"
0#
#2
0"
#3
0!
1>
1O
b11 =
0H
0R
0M
0<
08
06
b1010011 %
b1010011 +
b1010011 .
b1010011 G
14
1P
0K
b0 ;
b0 7
b10 5
b1 3
1N
1J
b1000100 )
b1000100 /
b1000100 D
b1010011 *
b1010011 0
b1010011 B
b10 C
b10 A
b10 &
b10 ,
b10 I
0L
1"
#4
0"
#5
1!
1H
1<
16
b1110101 %
b1110101 +
b1110101 .
b1110101 G
04
1K
b11 ;
b11 5
b10 3
0N
0J
b1100110 )
b1100110 /
b1100110 D
b1110101 *
b1110101 0
b1110101 B
b11 C
b11 A
b11 &
b11 ,
b11 I
1L
1"
#6
0"
#7
1@
1S
b11 ?
0V
0Q
0>
08
1!
1T
0O
b0 =
b10 7
1H
1R
1M
0<
16
b10010111 %
b10010111 +
b10010111 .
b10010111 G
14
0P
0K
b0 ;
b1 5
b1 3
1N
1J
b10001000 )
b10001000 /
b10001000 D
b10010111 *
b10010111 0
b10010111 B
b100 C
b100 A
b100 &
b100 ,
b100 I
0L
1"
#8
0"
#9
1H
1<
18
06
b10111001 %
b10111001 +
b10111001 .
b10111001 G
04
1K
b11 ;
b11 7
b0 5
b10 3
0N
0J
b10101010 )
b10101010 /
b10101010 D
b10111001 *
b10111001 0
b10111001 B
b101 C
b101 A
b101 &
b101 ,
b101 I
1L
1"
#10
0"
#11
0!
1>
1O
b11 =
0H
0R
0M
0<
18
06
b11011011 %
b11011011 +
b11011011 .
b11011011 G
14
1P
0K
b0 ;
b11 7
b10 5
b1 3
1N
1J
b11001100 )
b11001100 /
b11001100 D
b11011011 *
b11011011 0
b11011011 B
b110 C
b110 A
b110 &
b110 ,
b110 I
0L
1"
#12
0"
#13
1!
1H
1<
16
b11111101 %
b11111101 +
b11111101 .
b11111101 G
04
1K
b11 ;
b11 5
b10 3
0N
0J
b11101110 )
b11101110 /
b11101110 D
b11111101 *
b11111101 0
b11111101 B
b111 C
b111 A
b111 &
b111 ,
b111 I
1L
1"
#14
0"
#15
1W
0U
02
0:
0$
0@
1-
1F
1X
0S
b0 ?
1V
1Q
0>
08
1!
0T
0O
b0 =
b1 7
0H
1R
1M
0<
06
b0 %
b0 +
b0 .
b0 G
04
0P
0K
b0 ;
b1 5
b1 3
1N
1J
b0 )
b0 /
b0 D
b11111 *
b11111 0
b11111 B
b0 C
b0 A
b1000 &
b1000 ,
b1000 I
0L
1"
#16
0"
#17
0H
1<
b100010 %
b100010 +
b100010 .
b100010 G
14
1K
b11 ;
b0 7
b0 5
b10 3
0N
0J
b100010 )
b100010 /
b100010 D
b110001 *
b110001 0
b110001 B
b1 C
b1 A
b1001 &
b1001 ,
b1001 I
1L
1"
#18
0"
#19
1>
16
1O
b11 =
0H
0R
0M
0<
b1000100 %
b1000100 +
b1000100 .
b1000100 G
04
1P
0K
b0 ;
b0 7
b10 5
b1 3
1N
1J
b1000100 )
b1000100 /
b1000100 D
b1010011 *
b1010011 0
b1010011 B
b10 C
b10 A
b1010 &
b1010 ,
b1010 I
0L
1"
#20
0"
#21
0H
1<
b1100110 %
b1100110 +
b1100110 .
b1100110 G
14
1K
b11 ;
b11 5
b10 3
0N
0J
b1100110 )
b1100110 /
b1100110 D
b1110101 *
b1110101 0
b1110101 B
b11 C
b11 A
b1011 &
b1011 ,
b1011 I
1L
1"
#22
0"
#23
1@
18
1S
b11 ?
0V
0Q
0>
06
1T
0O
b0 =
b10 7
0H
1R
1M
0<
b10001000 %
b10001000 +
b10001000 .
b10001000 G
04
0P
0K
b0 ;
b1 5
b1 3
1N
1J
b10001000 )
b10001000 /
b10001000 D
b10010111 *
b10010111 0
b10010111 B
b100 C
b100 A
b1100 &
b1100 ,
b1100 I
0L
1"
#24
0"
#25
0H
1<
b10101010 %
b10101010 +
b10101010 .
b10101010 G
14
1K
b11 ;
b11 7
b0 5
b10 3
0N
0J
b10101010 )
b10101010 /
b10101010 D
b10111001 *
b10111001 0
b10111001 B
b101 C
b101 A
b1101 &
b1101 ,
b1101 I
1L
1"
#26
0"
#27
1>
16
1O
b11 =
0H
0R
0M
0<
b11001100 %
b11001100 +
b11001100 .
b11001100 G
04
1P
0K
b0 ;
b11 7
b10 5
b1 3
1N
1J
b11001100 )
b11001100 /
b11001100 D
b11011011 *
b11011011 0
b11011011 B
b110 C
b110 A
b1110 &
b1110 ,
b1110 I
0L
1"
#28
0"
#29
0H
1<
b11101110 %
b11101110 +
b11101110 .
b11101110 G
14
1K
b11 ;
b11 5
b10 3
0N
0J
b11101110 )
b11101110 /
b11101110 D
b11111101 *
b11111101 0
b11111101 B
b111 C
b111 A
b1111 &
b1111 ,
b1111 I
1L
1"
#30
0"
#31
0W
1U
12
1:
1$
0@
0-
0F
0X
0S
b0 ?
1V
1Q
0>
16
0T
0O
b0 =
b1 7
1H
1R
1M
0<
b11111 %
b11111 +
b11111 .
b11111 G
14
0P
0K
b0 ;
b1 5
b1 3
1N
1J
b0 )
b0 /
b0 D
b11111 *
b11111 0
b11111 B
b0 C
b0 A
b0 &
b0 ,
b0 I
0L
1"
#32
0"
#33
1H
1<
08
06
b110001 %
b110001 +
b110001 .
b110001 G
04
1K
b11 ;
b0 7
b0 5
b10 3
0N
0J
b100010 )
b100010 /
b100010 D
b110001 *
b110001 0
b110001 B
b1 C
b1 A
b1 &
b1 ,
b1 I
1L
1"
#34
0"
#35
0!
1>
1O
b11 =
0H
0R
0M
0<
08
06
b1010011 %
b1010011 +
b1010011 .
b1010011 G
14
1P
0K
b0 ;
b0 7
b10 5
b1 3
1N
1J
b1000100 )
b1000100 /
b1000100 D
b1010011 *
b1010011 0
b1010011 B
b10 C
b10 A
b10 &
b10 ,
b10 I
0L
1"
#36
0"
#37
1!
1H
1<
16
b1110101 %
b1110101 +
b1110101 .
b1110101 G
04
1K
b11 ;
b11 5
b10 3
0N
0J
b1100110 )
b1100110 /
b1100110 D
b1110101 *
b1110101 0
b1110101 B
b11 C
b11 A
b11 &
b11 ,
b11 I
1L
1"
#38
0"
#39
1@
1S
b11 ?
0V
0Q
0>
08
1!
1T
0O
b0 =
b10 7
1H
1R
1M
0<
16
b10010111 %
b10010111 +
b10010111 .
b10010111 G
14
0P
0K
b0 ;
b1 5
b1 3
1N
1J
b10001000 )
b10001000 /
b10001000 D
b10010111 *
b10010111 0
b10010111 B
b100 C
b100 A
b100 &
b100 ,
b100 I
0L
1"
#40
0"
#41
1H
1<
18
06
b10111001 %
b10111001 +
b10111001 .
b10111001 G
04
1K
b11 ;
b11 7
b0 5
b10 3
0N
0J
b10101010 )
b10101010 /
b10101010 D
b10111001 *
b10111001 0
b10111001 B
b101 C
b101 A
b101 &
b101 ,
b101 I
1L
1"
#42
0"
#43
0!
1>
1O
b11 =
0H
0R
0M
0<
18
06
b11011011 %
b11011011 +
b11011011 .
b11011011 G
14
1P
0K
b0 ;
b11 7
b10 5
b1 3
1N
1J
b11001100 )
b11001100 /
b11001100 D
b11011011 *
b11011011 0
b11011011 B
b110 C
b110 A
b110 &
b110 ,
b110 I
0L
1"
#44
0"
#45
1!
1H
1<
16
b11111101 %
b11111101 +
b11111101 .
b11111101 G
04
1K
b11 ;
b11 5
b10 3
0N
0J
b11101110 )
b11101110 /
b11101110 D
b11111101 *
b11111101 0
b11111101 B
b111 C
b111 A
b111 &
b111 ,
b111 I
1L
1"
#46
0"
#47
1W
0U
02
0:
0$
0@
1-
1F
1X
0S
b0 ?
1V
1Q
0>
08
1!
0T
0O
b0 =
b1 7
0H
1R
1M
0<
06
b0 %
b0 +
b0 .
b0 G
04
0P
0K
b0 ;
b1 5
b1 3
1N
1J
b0 )
b0 /
b0 D
b11111 *
b11111 0
b11111 B
b0 C
b0 A
b1000 &
b1000 ,
b1000 I
0L
1"
#48
0"
#49
0H
1<
b100010 %
b100010 +
b100010 .
b100010 G
14
1K
b11 ;
b0 7
b0 5
b10 3
0N
0J
b100010 )
b100010 /
b100010 D
b110001 *
b110001 0
b110001 B
b1 C
b1 A
b1001 &
b1001 ,
b1001 I
1L
1"
#50
0"
#51
1>
16
1O
b11 =
0H
0R
0M
0<
b1000100 %
b1000100 +
b1000100 .
b1000100 G
04
1P
0K
b0 ;
b0 7
b10 5
b1 3
1N
1J
b1000100 )
b1000100 /
b1000100 D
b1010011 *
b1010011 0
b1010011 B
b10 C
b10 A
b1010 &
b1010 ,
b1010 I
0L
1"
#52
0"
#53
0H
1<
b1100110 %
b1100110 +
b1100110 .
b1100110 G
14
1K
b11 ;
b11 5
b10 3
0N
0J
b1100110 )
b1100110 /
b1100110 D
b1110101 *
b1110101 0
b1110101 B
b11 C
b11 A
b1011 &
b1011 ,
b1011 I
1L
1"
#54
0"
#55
1@
18
1S
b11 ?
0V
0Q
0>
06
1T
0O
b0 =
b10 7
0H
1R
1M
0<
b10001000 %
b10001000 +
b10001000 .
b10001000 G
04
0P
0K
b0 ;
b1 5
b1 3
1N
1J
b10001000 )
b10001000 /
b10001000 D
b10010111 *
b10010111 0
b10010111 B
b100 C
b100 A
b1100 &
b1100 ,
b1100 I
0L
1"
#56
0"
#57
0H
1<
b10101010 %
b10101010 +
b10101010 .
b10101010 G
14
1K
b11 ;
b11 7
b0 5
b10 3
0N
0J
b10101010 )
b10101010 /
b10101010 D
b10111001 *
b10111001 0
b10111001 B
b101 C
b101 A
b1101 &
b1101 ,
b1101 I
1L
1"
#58
0"
#59
1>
16
1O
b11 =
0H
0R
0M
0<
b11001100 %
b11001100 +
b11001100 .
b11001100 G
04
1P
0K
b0 ;
b11 7
b10 5
b1 3
1N
1J
b11001100 )
b11001100 /
b11001100 D
b11011011 *
b11011011 0
b11011011 B
b110 C
b110 A
b1110 &
b1110 ,
b1110 I
0L
1"
#60
0"
#61
0H
1<
b11101110 %
b11101110 +
b11101110 .
b11101110 G
14
1K
b11 ;
b11 5
b10 3
0N
0J
b11101110 )
b11101110 /
b11101110 D
b11111101 *
b11111101 0
b11111101 B
b111 C
b111 A
b1111 &
b1111 ,
b1111 I
1L
1"
#62
0"
#63
0W
1U
12
1:
1$
0@
0-
0F
0X
0S
b0 ?
1V
1Q
0>
16
0T
0O
b0 =
b1 7
1H
1R
1M
0<
b11111 %
b11111 +
b11111 .
b11111 G
14
0P
0K
b0 ;
b1 5
b1 3
1N
1J
b0 )
b0 /
b0 D
b11111 *
b11111 0
b11111 B
b0 C
b0 A
b0 &
b0 ,
b0 I
0L
1"
#64
0"
#65
1H
1<
08
06
b110001 %
b110001 +
b110001 .
b110001 G
04
1K
b11 ;
b0 7
b0 5
b10 3
0N
0J
b100010 )
b100010 /
b100010 D
b110001 *
b110001 0
b110001 B
b1 C
b1 A
b1 &
b1 ,
b1 I
1L
1"
#66
0"
#67
0!
1>
1O
b11 =
0H
0R
0M
0<
08
06
b1010011 %
b1010011 +
b1010011 .
b1010011 G
14
1P
0K
b0 ;
b0 7
b10 5
b1 3
1N
1J
b1000100 )
b1000100 /
b1000100 D
b1010011 *
b1010011 0
b1010011 B
b10 C
b10 A
b10 &
b10 ,
b10 I
0L
1"
#68
0"
#69
1!
1H
1<
16
b1110101 %
b1110101 +
b1110101 .
b1110101 G
04
1K
b11 ;
b11 5
b10 3
0N
0J
b1100110 )
b1100110 /
b1100110 D
b1110101 *
b1110101 0
b1110101 B
b11 C
b11 A
b11 &
b11 ,
b11 I
1L
1"
#70
0"
#71
1@
1S
b11 ?
0V
0Q
0>
08
1!
1T
0O
b0 =
b10 7
1H
1R
1M
0<
16
b10010111 %
b10010111 +
b10010111 .
b10010111 G
14
0P
0K
b0 ;
b1 5
b1 3
1N
1J
b10001000 )
b10001000 /
b10001000 D
b10010111 *
b10010111 0
b10010111 B
b100 C
b100 A
b100 &
b100 ,
b100 I
0L
1"
#72
0"
#73
1H
1<
18
06
b10111001 %
b10111001 +
b10111001 .
b10111001 G
04
1K
b11 ;
b11 7
b0 5
b10 3
0N
0J
b10101010 )
b10101010 /
b10101010 D
b10111001 *
b10111001 0
b10111001 B
b101 C
b101 A
b101 &
b101 ,
b101 I
1L
1"
#74
0"
#75
0!
1>
1O
b11 =
0H
0R
0M
0<
18
06
b11011011 %
b11011011 +
b11011011 .
b11011011 G
14
1P
0K
b0 ;
b11 7
b10 5
b1 3
1N
1J
b11001100 )
b11001100 /
b11001100 D
b11011011 *
b11011011 0
b11011011 B
b110 C
b110 A
b110 &
b110 ,
b110 I
0L
1"
#76
0"
#77
1!
1H
1<
16
b11111101 %
b11111101 +
b11111101 .
b11111101 G
04
1K
b11 ;
b11 5
b10 3
0N
0J
b11101110 )
b11101110 /
b11101110 D
b11111101 *
b11111101 0
b11111101 B
b111 C
b111 A
b111 &
b111 ,
b111 I
1L
1"
#78
0"
#79
1W
0U
02
0:
0$
0@
1-
1F
1X
0S
b0 ?
1V
1Q
0>
08
1!
0T
0O
b0 =
b1 7
0H
1R
1M
0<
06
b0 %
b0 +
b0 .
b0 G
04
0P
0K
b0 ;
b1 5
b1 3
1N
1J
b0 )
b0 /
b0 D
b11111 *
b11111 0
b11111 B
b0 C
b0 A
b1000 &
b1000 ,
b1000 I
0L
1"
#80
0"
#81
0H
1<
b100010 %
b100010 +
b100010 .
b100010 G
14
1K
b11 ;
b0 7
b0 5
b10 3
0N
0J
b100010 )
b100010 /
b100010 D
b110001 *
b110001 0
b110001 B
b1 C
b1 A
b1001 &
b1001 ,
b1001 I
1L
1"
#82
0"
#83
1>
16
1O
b11 =
0H
0R
0M
0<
b1000100 %
b1000100 +
b1000100 .
b1000100 G
04
1P
0K
b0 ;
b0 7
b10 5
b1 3
1N
1J
b1000100 )
b1000100 /
b1000100 D
b1010011 *
b1010011 0
b1010011 B
b10 C
b10 A
b1010 &
b1010 ,
b1010 I
0L
1"
#84
0"
#85
0H
1<
b1100110 %
b1100110 +
b1100110 .
b1100110 G
14
1K
b11 ;
b11 5
b10 3
0N
0J
b1100110 )
b1100110 /
b1100110 D
b1110101 *
b1110101 0
b1110101 B
b11 C
b11 A
b1011 &
b1011 ,
b1011 I
1L
1"
#86
0"
#87
1@
18
1S
b11 ?
0V
0Q
0>
06
1T
0O
b0 =
b10 7
0H
1R
1M
0<
b10001000 %
b10001000 +
b10001000 .
b10001000 G
04
0P
0K
b0 ;
b1 5
b1 3
1N
1J
b10001000 )
b10001000 /
b10001000 D
b10010111 *
b10010111 0
b10010111 B
b100 C
b100 A
b1100 &
b1100 ,
b1100 I
0L
1"
#88
0"
#89
0H
1<
b10101010 %
b10101010 +
b10101010 .
b10101010 G
14
1K
b11 ;
b11 7
b0 5
b10 3
0N
0J
b10101010 )
b10101010 /
b10101010 D
b10111001 *
b10111001 0
b10111001 B
b101 C
b101 A
b1101 &
b1101 ,
b1101 I
1L
1"
#90
0"
#91
1>
16
1O
b11 =
0H
0R
0M
0<
b11001100 %
b11001100 +
b11001100 .
b11001100 G
04
1P
0K
b0 ;
b11 7
b10 5
b1 3
1N
1J
b11001100 )
b11001100 /
b11001100 D
b11011011 *
b11011011 0
b11011011 B
b110 C
b110 A
b1110 &
b1110 ,
b1110 I
0L
1"
#92
0"
#93
0H
1<
b11101110 %
b11101110 +
b11101110 .
b11101110 G
14
1K
b11 ;
b11 5
b10 3
0N
0J
b11101110 )
b11101110 /
b11101110 D
b11111101 *
b11111101 0
b11111101 B
b111 C
b111 A
b1111 &
b1111 ,
b1111 I
1L
1"
#94
0"
#95
0W
1U
12
1:
1$
0@
0-
0F
0X
0S
b0 ?
1V
1Q
0>
16
0T
0O
b0 =
b1 7
1H
1R
1M
0<
b11111 %
b11111 +
b11111 .
b11111 G
14
0P
0K
b0 ;
b1 5
b1 3
1N
1J
b0 )
b0 /
b0 D
b11111 *
b11111 0
b11111 B
b0 C
b0 A
b0 &
b0 ,
b0 I
0L
1"
#96
0"
#97
1H
1<
08
06
b110001 %
b110001 +
b110001 .
b110001 G
04
1K
b11 ;
b0 7
b0 5
b10 3
0N
0J
b100010 )
b100010 /
b100010 D
b110001 *
b110001 0
b110001 B
b1 C
b1 A
b1 &
b1 ,
b1 I
1L
1"
#98
0"
#99
0!
1>
1O
b11 =
0H
0R
0M
0<
08
06
b1010011 %
b1010011 +
b1010011 .
b1010011 G
14
1P
0K
b0 ;
b0 7
b10 5
b1 3
1N
1J
b1000100 )
b1000100 /
b1000100 D
b1010011 *
b1010011 0
b1010011 B
b10 C
b10 A
b10 &
b10 ,
b10 I
0L
1"
#100
0"
#101
1!
1H
1<
16
b1110101 %
b1110101 +
b1110101 .
b1110101 G
04
1K
b11 ;
b11 5
b10 3
0N
0J
b1100110 )
b1100110 /
b1100110 D
b1110101 *
b1110101 0
b1110101 B
b11 C
b11 A
b11 &
b11 ,
b11 I
1L
1"
