2018.v
// V.Aravindan
// 2017B4A70849P
module MUX_SMALL(out,in,sel);
input [1:0]in;
input sel;
output out;
assign out=sel?in[1]:in[0];
endmodule

module MUX_BIG(out,in,sel);
input [7:0]in;
input [2:0]sel;
output out;
wire w00,w01,w10,w11,w1,w0;
MUX_SMALL m1(w00,{in[4],in[0]},sel[2]);
MUX_SMALL m2(w01,{in[5],in[1]},sel[2]);
MUX_SMALL m3(w10,{in[6],in[2]},sel[2]);
MUX_SMALL m4(w11,{in[7],in[3]},sel[2]);
MUX_SMALL m5(w1,{w11,w01},sel[1]);
MUX_SMALL m6(w0,{w10,w00},sel[1]);
MUX_SMALL m7(out,{w1,w0},sel[0]);
endmodule

module TFF(out,t,clear,clk);
input t,clear,clk;
output reg out;
always@(posedge clk)
  begin
    if(t)
      out=~out;
    else
      out=out;
  end
always@(clear)
  begin
    if(clear)
      out<=0;
  end
endmodule

module COUNTER_4BIT(Q,clear,clk);
input clear,clk;
output [3:0]Q;
wire w1,w2;
TFF tff1(Q[0],1'b1,clear,clk);
TFF tff2(Q[1],Q[0],clear,clk);
and a1(w1,Q[0],Q[1]);
TFF tff3(Q[2],w1,clear,clk);
and a2(w2,Q[1],Q[2]);
TFF tff4(Q[3],w2,clear,clk);
endmodule

module COUNTER_3BIT(Q,clear,clk);
input clear,clk;
output [2:0]Q;
wire w1;
TFF tff1(Q[0],1'b1,clear,clk);
TFF tff2(Q[1],Q[0],clear,clk);
and a1(w1,Q[0],Q[1]);
TFF tff3(Q[2],w1,clear,clk);
endmodule

module MEMORY(D,A);
input [3:0]A;
output reg [7:0]D;
reg [7:0]memory[0:15];
initial
  begin
    memory[0]=8'hCC;
    memory[1]=8'hAA;
    memory[2]=8'hCC;
    memory[3]=8'hAA;
    memory[4]=8'hCC;
    memory[5]=8'hAA;
    memory[6]=8'hCC;
    memory[7]=8'hAA;
    memory[8]=8'hCC;
    memory[9]=8'hAA;
    memory[10]=8'hCC;
    memory[11]=8'hAA;
    memory[12]=8'hCC;
    memory[13]=8'hAA;
    memory[14]=8'hCC;
    memory[15]=8'hAA;
  end
always@(A)
  begin
    case(A)
      4'd0: D=memory[0];
      4'd1: D=memory[1];
      4'd2: D=memory[2];
      4'd3: D=memory[3];
      4'd4: D=memory[4];
      4'd5: D=memory[5];
      4'd6: D=memory[6];
      4'd7: D=memory[7];
      4'd8: D=memory[8];
      4'd9: D=memory[9];
      4'd10: D=memory[10];
      4'd11: D=memory[11];
      4'd12: D=memory[12];
      4'd13: D=memory[13];
      4'd14: D=memory[14];
      4'd15: D=memory[15];
    endcase
  end
endmodule

module INTG(out,clear,clk1);
  input clk1,clear;
  output out;
  wire [3:0]A;
  wire [2:0]S;
  wire [7:0]I;
  wire clk2;
  COUNTER_3BIT c3(S,clear,clk1);
  assign clk2=S[2] & S[1] & S[0];
  COUNTER_4BIT c4(A,clear,clk2);
  MEMORY m(I,A);
  MUX_BIG mux(out,I,S);
endmodule

module testbench;
  initial
    begin
      $dumpfile("2018.vcd");
      $dumpvars;
    end

  reg clk1,clear;
  wire out;

  INTG i(out,clear,clk1);

  always
    #0.5 clk1=~clk1;

  initial
    $monitor($time,"   clk1=%b |||||| output=%b ",clk1,out);

  initial
    begin
      clk1=1'b0; clear=1'b1;
      #1 clear=1'b0;
      #200 $finish;
    end

endmodule

2018.vcd
$date
	Sat Nov 07 21:12:40 2020
$end
$version
	Icarus Verilog
$end
$timescale
	1s
$end
$scope module testbench $end
$var wire 1 ! out $end
$var reg 1 " clear $end
$var reg 1 # clk1 $end
$scope module i $end
$var wire 1 " clear $end
$var wire 1 # clk1 $end
$var wire 1 $ clk2 $end
$var wire 1 ! out $end
$var wire 3 % S [2:0] $end
$var wire 8 & I [7:0] $end
$var wire 4 ' A [3:0] $end
$scope module c3 $end
$var wire 1 " clear $end
$var wire 1 # clk $end
$var wire 1 ( w1 $end
$var wire 3 ) Q [2:0] $end
$scope module tff1 $end
$var wire 1 " clear $end
$var wire 1 # clk $end
$var wire 1 * t $end
$var reg 1 + out $end
$upscope $end
$scope module tff2 $end
$var wire 1 " clear $end
$var wire 1 # clk $end
$var wire 1 , t $end
$var reg 1 - out $end
$upscope $end
$scope module tff3 $end
$var wire 1 " clear $end
$var wire 1 # clk $end
$var wire 1 ( t $end
$var reg 1 . out $end
$upscope $end
$upscope $end
$scope module c4 $end
$var wire 1 " clear $end
$var wire 1 $ clk $end
$var wire 1 / w1 $end
$var wire 1 0 w2 $end
$var wire 4 1 Q [3:0] $end
$scope module tff1 $end
$var wire 1 " clear $end
$var wire 1 $ clk $end
$var wire 1 2 t $end
$var reg 1 3 out $end
$upscope $end
$scope module tff2 $end
$var wire 1 " clear $end
$var wire 1 $ clk $end
$var wire 1 4 t $end
$var reg 1 5 out $end
$upscope $end
$scope module tff3 $end
$var wire 1 " clear $end
$var wire 1 $ clk $end
$var wire 1 / t $end
$var reg 1 6 out $end
$upscope $end
$scope module tff4 $end
$var wire 1 " clear $end
$var wire 1 $ clk $end
$var wire 1 0 t $end
$var reg 1 7 out $end
$upscope $end
$upscope $end
$scope module m $end
$var wire 4 8 A [3:0] $end
$var reg 8 9 D [7:0] $end
$upscope $end
$scope module mux $end
$var wire 8 : in [7:0] $end
$var wire 3 ; sel [2:0] $end
$var wire 1 < w11 $end
$var wire 1 = w10 $end
$var wire 1 > w1 $end
$var wire 1 ? w01 $end
$var wire 1 @ w00 $end
$var wire 1 A w0 $end
$var wire 1 ! out $end
$scope module m1 $end
$var wire 2 B in [1:0] $end
$var wire 1 C sel $end
$var wire 1 @ out $end
$upscope $end
$scope module m2 $end
$var wire 2 D in [1:0] $end
$var wire 1 E sel $end
$var wire 1 ? out $end
$upscope $end
$scope module m3 $end
$var wire 2 F in [1:0] $end
$var wire 1 G sel $end
$var wire 1 = out $end
$upscope $end
$scope module m4 $end
$var wire 2 H in [1:0] $end
$var wire 1 I sel $end
$var wire 1 < out $end
$upscope $end
$scope module m5 $end
$var wire 2 J in [1:0] $end
$var wire 1 K sel $end
$var wire 1 > out $end
$upscope $end
$scope module m6 $end
$var wire 2 L in [1:0] $end
$var wire 1 M sel $end
$var wire 1 A out $end
$upscope $end
$scope module m7 $end
$var wire 2 N in [1:0] $end
$var wire 1 O sel $end
$var wire 1 ! out $end
$upscope $end
$upscope $end
$upscope $end
$upscope $end
$enddefinitions $end
#0
$dumpvars
0O
b0 N
0M
b10 L
0K
b10 J
0I
b11 H
0G
b11 F
0E
b0 D
0C
b0 B
0A
0@
0?
0>
1=
1<
b0 ;
b11001100 :
b11001100 9
b0 8
07
06
05
04
03
12
b0 1
00
0/
0.
0-
0,
0+
1*
b0 )
0(
b0 '
b11001100 &
b0 %
0$
0#
1"
0!
$end
#1
1O
1,
b1 %
b1 )
b1 ;
1+
0"
1#
#2
0#
#3
1!
1>
b11 N
1A
1K
1M
0O
0,
1-
b10 %
b10 )
b10 ;
0+
1#
#4
0#
#5
1(
1O
1,
b11 %
b11 )
b11 ;
1+
1#
#6
0#
#7
0!
0>
b0 N
0A
0(
1C
1E
1G
1I
0K
0M
0O
0,
1.
0-
b100 %
b100 )
b100 ;
0+
1#
#8
0#
#9
1O
1,
b101 %
b101 )
b101 ;
1+
1#
#10
0#
#11
1!
1>
b11 N
1A
1K
1M
0O
0,
1-
b110 %
b110 )
b110 ;
0+
1#
#12
0#
#13
b10 N
0A
b11 J
1?
b0 L
0=
b11 D
b0 F
14
b10101010 &
b10101010 9
b10101010 :
b1 '
b1 1
b1 8
13
1(
1$
1O
1,
b111 %
b111 )
b111 ;
1+
1#
#14
0#
#15
0!
0(
0$
0C
0E
0G
0I
0K
0M
0O
0,
0.
0-
b0 %
b0 )
b0 ;
0+
1#
#16
0#
#17
1!
1O
1,
b1 %
b1 )
b1 ;
1+
1#
#18
0#
#19
0!
1K
1M
0O
0,
1-
b10 %
b10 )
b10 ;
0+
1#
#20
0#
#21
1!
1(
1O
1,
b11 %
b11 )
b11 ;
1+
1#
#22
0#
#23
0!
0(
1C
1E
1G
1I
0K
0M
0O
0,
1.
0-
b100 %
b100 )
b100 ;
0+
1#
#24
0#
#25
1!
1O
1,
b101 %
b101 )
b101 ;
1+
1#
#26
0#
#27
0!
1K
1M
0O
0,
1-
b110 %
b110 )
b110 ;
0+
1#
#28
0#
#29
b11 N
1A
b10 J
0?
b10 L
1=
b0 D
b11 F
04
b11001100 &
b11001100 9
b11001100 :
15
b10 '
b10 1
b10 8
03
1!
1(
1$
1O
1,
b111 %
b111 )
b111 ;
1+
1#
#30
0#
#31
0!
0>
b0 N
0A
0(
0$
0C
0E
0G
0I
0K
0M
0O
0,
0.
0-
b0 %
b0 )
b0 ;
0+
1#
#32
0#
#33
1O
1,
b1 %
b1 )
b1 ;
1+
1#
#34
0#
#35
1!
1>
b11 N
1A
1K
1M
0O
0,
1-
b10 %
b10 )
b10 ;
0+
1#
#36
0#
#37
1(
1O
1,
b11 %
b11 )
b11 ;
1+
1#
#38
0#
#39
0!
0>
b0 N
0A
0(
1C
1E
1G
1I
0K
0M
0O
0,
1.
0-
b100 %
b100 )
b100 ;
0+
1#
#40
0#
#41
1O
1,
b101 %
b101 )
b101 ;
1+
1#
#42
0#
#43
1!
1>
b11 N
1A
1K
1M
0O
0,
1-
b110 %
b110 )
b110 ;
0+
1#
#44
0#
#45
b10 N
0A
b11 J
1?
b0 L
0=
1/
b11 D
b0 F
14
b10101010 &
b10101010 9
b10101010 :
b11 '
b11 1
b11 8
13
1(
1$
1O
1,
b111 %
b111 )
b111 ;
1+
1#
#46
0#
#47
0!
0(
0$
0C
0E
0G
0I
0K
0M
0O
0,
0.
0-
b0 %
b0 )
b0 ;
0+
1#
#48
0#
#49
1!
1O
1,
b1 %
b1 )
b1 ;
1+
1#
#50
0#
#51
0!
1K
1M
0O
0,
1-
b10 %
b10 )
b10 ;
0+
1#
#52
0#
#53
1!
1(
1O
1,
b11 %
b11 )
b11 ;
1+
1#
#54
0#
#55
0!
0(
1C
1E
1G
1I
0K
0M
0O
0,
1.
0-
b100 %
b100 )
b100 ;
0+
1#
#56
0#
#57
1!
1O
1,
b101 %
b101 )
b101 ;
1+
1#
#58
0#
#59
0!
1K
1M
0O
0,
1-
b110 %
b110 )
b110 ;
0+
1#
#60
0#
#61
b11 N
1A
b10 J
0?
b10 L
1=
0/
b0 D
b11 F
04
b11001100 &
b11001100 9
b11001100 :
16
05
b100 '
b100 1
b100 8
03
1!
1(
1$
1O
1,
b111 %
b111 )
b111 ;
1+
1#
#62
0#
#63
0!
0>
b0 N
0A
0(
0$
0C
0E
0G
0I
0K
0M
0O
0,
0.
0-
b0 %
b0 )
b0 ;
0+
1#
#64
0#
#65
1O
1,
b1 %
b1 )
b1 ;
1+
1#
#66
0#
#67
1!
1>
b11 N
1A
1K
1M
0O
0,
1-
b10 %
b10 )
b10 ;
0+
1#
#68
0#
#69
1(
1O
1,
b11 %
b11 )
b11 ;
1+
1#
#70
0#
#71
0!
0>
b0 N
0A
0(
1C
1E
1G
1I
0K
0M
0O
0,
1.
0-
b100 %
b100 )
b100 ;
0+
1#
#72
0#
#73
1O
1,
b101 %
b101 )
b101 ;
1+
1#
#74
0#
#75
1!
1>
b11 N
1A
1K
1M
0O
0,
1-
b110 %
b110 )
b110 ;
0+
1#
#76
0#
#77
b10 N
0A
b11 J
1?
b0 L
0=
b11 D
b0 F
14
b10101010 &
b10101010 9
b10101010 :
b101 '
b101 1
b101 8
13
1(
1$
1O
1,
b111 %
b111 )
b111 ;
1+
1#
#78
0#
#79
0!
0(
0$
0C
0E
0G
0I
0K
0M
0O
0,
0.
0-
b0 %
b0 )
b0 ;
0+
1#
#80
0#
#81
1!
1O
1,
b1 %
b1 )
b1 ;
1+
1#
#82
0#
#83
0!
1K
1M
0O
0,
1-
b10 %
b10 )
b10 ;
0+
1#
#84
0#
#85
1!
1(
1O
1,
b11 %
b11 )
b11 ;
1+
1#
#86
0#
#87
0!
0(
1C
1E
1G
1I
0K
0M
0O
0,
1.
0-
b100 %
b100 )
b100 ;
0+
1#
#88
0#
#89
1!
1O
1,
b101 %
b101 )
b101 ;
1+
1#
#90
0#
#91
0!
1K
1M
0O
0,
1-
b110 %
b110 )
b110 ;
0+
1#
#92
0#
#93
b11 N
1A
b10 J
0?
b10 L
1=
10
b0 D
b11 F
04
b11001100 &
b11001100 9
b11001100 :
15
b110 '
b110 1
b110 8
03
1!
1(
1$
1O
1,
b111 %
b111 )
b111 ;
1+
1#
#94
0#
#95
0!
0>
b0 N
0A
0(
0$
0C
0E
0G
0I
0K
0M
0O
0,
0.
0-
b0 %
b0 )
b0 ;
0+
1#
#96
0#
#97
1O
1,
b1 %
b1 )
b1 ;
1+
1#
#98
0#
#99
1!
1>
b11 N
1A
1K
1M
0O
0,
1-
b10 %
b10 )
b10 ;
0+
1#
#100
0#
#101
1(
1O
1,
b11 %
b11 )
b11 ;
1+
1#
#102
0#
#103
0!
0>
b0 N
0A
0(
1C
1E
1G
1I
0K
0M
0O
0,
1.
0-
b100 %
b100 )
b100 ;
0+
1#
#104
0#
#105
1O
1,
b101 %
b101 )
b101 ;
1+
1#
#106
0#
#107
1!
1>
b11 N
1A
1K
1M
0O
0,
1-
b110 %
b110 )
b110 ;
0+
1#
#108
0#
#109
b10 N
0A
b11 J
1?
b0 L
0=
1/
b11 D
b0 F
14
b10101010 &
b10101010 9
b10101010 :
13
b1111 '
b1111 1
b1111 8
17
1(
1$
1O
1,
b111 %
b111 )
b111 ;
1+
1#
#110
0#
#111
0!
0(
0$
0C
0E
0G
0I
0K
0M
0O
0,
0.
0-
b0 %
b0 )
b0 ;
0+
1#
#112
0#
#113
1!
1O
1,
b1 %
b1 )
b1 ;
1+
1#
#114
0#
#115
0!
1K
1M
0O
0,
1-
b10 %
b10 )
b10 ;
0+
1#
#116
0#
#117
1!
1(
1O
1,
b11 %
b11 )
b11 ;
1+
1#
#118
0#
#119
0!
0(
1C
1E
1G
1I
0K
0M
0O
0,
1.
0-
b100 %
b100 )
b100 ;
0+
1#
#120
0#
#121
1!
1O
1,
b101 %
b101 )
b101 ;
1+
1#
#122
0#
#123
0!
1K
1M
0O
0,
1-
b110 %
b110 )
b110 ;
0+
1#
#124
0#
#125
b11 N
1A
b10 J
0?
b10 L
1=
00
0/
b0 D
b11 F
04
b11001100 &
b11001100 9
b11001100 :
07
06
05
b0 '
b0 1
b0 8
03
1!
1(
1$
1O
1,
b111 %
b111 )
b111 ;
1+
1#
#126
0#
#127
0!
0>
b0 N
0A
0(
0$
0C
0E
0G
0I
0K
0M
0O
0,
0.
0-
b0 %
b0 )
b0 ;
0+
1#
#128
0#
#129
1O
1,
b1 %
b1 )
b1 ;
1+
1#
#130
0#
#131
1!
1>
b11 N
1A
1K
1M
0O
0,
1-
b10 %
b10 )
b10 ;
0+
1#
#132
0#
#133
1(
1O
1,
b11 %
b11 )
b11 ;
1+
1#
#134
0#
#135
0!
0>
b0 N
0A
0(
1C
1E
1G
1I
0K
0M
0O
0,
1.
0-
b100 %
b100 )
b100 ;
0+
1#
#136
0#
#137
1O
1,
b101 %
b101 )
b101 ;
1+
1#
#138
0#
#139
1!
1>
b11 N
1A
1K
1M
0O
0,
1-
b110 %
b110 )
b110 ;
0+
1#
#140
0#
#141
b10 N
0A
b11 J
1?
b0 L
0=
b11 D
b0 F
14
b10101010 &
b10101010 9
b10101010 :
b1 '
b1 1
b1 8
13
1(
1$
1O
1,
b111 %
b111 )
b111 ;
1+
1#
#142
0#
#143
0!
0(
0$
0C
0E
0G
0I
0K
0M
0O
0,
0.
0-
b0 %
b0 )
b0 ;
0+
1#
#144
0#
#145
1!
1O
1,
b1 %
b1 )
b1 ;
1+
1#
#146
0#
#147
0!
1K
1M
0O
0,
1-
b10 %
b10 )
b10 ;
0+
1#
#148
0#
#149
1!
1(
1O
1,
b11 %
b11 )
b11 ;
1+
1#
#150
0#
#151
0!
0(
1C
1E
1G
1I
0K
0M
0O
0,
1.
0-
b100 %
b100 )
b100 ;
0+
1#
#152
0#
#153
1!
1O
1,
b101 %
b101 )
b101 ;
1+
1#
#154
0#
#155
0!
1K
1M
0O
0,
1-
b110 %
b110 )
b110 ;
0+
1#
#156
0#
#157
b11 N
1A
b10 J
0?
b10 L
1=
b0 D
b11 F
04
b11001100 &
b11001100 9
b11001100 :
15
b10 '
b10 1
b10 8
03
1!
1(
1$
1O
1,
b111 %
b111 )
b111 ;
1+
1#
#158
0#
#159
0!
0>
b0 N
0A
0(
0$
0C
0E
0G
0I
0K
0M
0O
0,
0.
0-
b0 %
b0 )
b0 ;
0+
1#
#160
0#
#161
1O
1,
b1 %
b1 )
b1 ;
1+
1#
#162
0#
#163
1!
1>
b11 N
1A
1K
1M
0O
0,
1-
b10 %
b10 )
b10 ;
0+
1#
#164
0#
#165
1(
1O
1,
b11 %
b11 )
b11 ;
1+
1#
#166
0#
#167
0!
0>
b0 N
0A
0(
1C
1E
1G
1I
0K
0M
0O
0,
1.
0-
b100 %
b100 )
b100 ;
0+
1#
#168
0#
#169
1O
1,
b101 %
b101 )
b101 ;
1+
1#
#170
0#
#171
1!
1>
b11 N
1A
1K
1M
0O
0,
1-
b110 %
b110 )
b110 ;
0+
1#
#172
0#
#173
b10 N
0A
b11 J
1?
b0 L
0=
1/
b11 D
b0 F
14
b10101010 &
b10101010 9
b10101010 :
b11 '
b11 1
b11 8
13
1(
1$
1O
1,
b111 %
b111 )
b111 ;
1+
1#
#174
0#
#175
0!
0(
0$
0C
0E
0G
0I
0K
0M
0O
0,
0.
0-
b0 %
b0 )
b0 ;
0+
1#
#176
0#
#177
1!
1O
1,
b1 %
b1 )
b1 ;
1+
1#
#178
0#
#179
0!
1K
1M
0O
0,
1-
b10 %
b10 )
b10 ;
0+
1#
#180
0#
#181
1!
1(
1O
1,
b11 %
b11 )
b11 ;
1+
1#
#182
0#
#183
0!
0(
1C
1E
1G
1I
0K
0M
0O
0,
1.
0-
b100 %
b100 )
b100 ;
0+
1#
#184
0#
#185
1!
1O
1,
b101 %
b101 )
b101 ;
1+
1#
#186
0#
#187
0!
1K
1M
0O
0,
1-
b110 %
b110 )
b110 ;
0+
1#
#188
0#
#189
b11 N
1A
b10 J
0?
b10 L
1=
0/
b0 D
b11 F
04
b11001100 &
b11001100 9
b11001100 :
16
05
b100 '
b100 1
b100 8
03
1!
1(
1$
1O
1,
b111 %
b111 )
b111 ;
1+
1#
#190
0#
#191
0!
0>
b0 N
0A
0(
0$
0C
0E
0G
0I
0K
0M
0O
0,
0.
0-
b0 %
b0 )
b0 ;
0+
1#
#192
0#
#193
1O
1,
b1 %
b1 )
b1 ;
1+
1#
#194
0#
#195
1!
1>
b11 N
1A
1K
1M
0O
0,
1-
b10 %
b10 )
b10 ;
0+
1#
#196
0#
#197
1(
1O
1,
b11 %
b11 )
b11 ;
1+
1#
#198
0#
#199
0!
0>
b0 N
0A
0(
1C
1E
1G
1I
0K
0M
0O
0,
1.
0-
b100 %
b100 )
b100 ;
0+
1#
#200
0#
#201
1O
1,
b101 %
b101 )
b101 ;
1+
1#
