CAtest19.v
`timescale 1ms/100us

module MUX_2x1(out,in,sel);
input [1:0]in;
input sel;
output out;
assign out=(sel)?in[1]:in[0];
endmodule

module MUX_8x1(out,in,sel);
input [7:0]in;
input [2:0]sel;
output out;
assign out=(sel[2])?(sel[1]?(sel[0]?(in[7]):(in[6])):(sel[0]?(in[5]):(in[4]))):(sel[1]?(sel[0]?(in[3]):(in[2])):(sel[0]?(in[1]):(in[0])));
// always@*
  // $display($realtime,"  sel=%b in=%b out=%b",sel,in,out);
endmodule

module MUX_ARRAY(E,B,F);
input [7:0]B,F;
output [7:0]E;
genvar i;
generate
for(i=0;i<8;i=i+1) begin:mux_loop
  MUX_2x1 m(E[i],{B[i],1'b0},F[i]);
end
endgenerate
endmodule

module COUNTER_3BIT(out,clk,clear);
output reg [2:0]out;
input clk,clear;
always@(posedge clk)
    begin
      out<=out+1;
    end
always@(clear)
  begin
    if(clear)
     out<=3'b000;
    end
endmodule

module DECODER(B,A,EN);
  input [2:0]A;
  input EN;
  output reg [7:0]B;
  always@(A)
  begin
    if(EN)
    begin
      case(A)
        3'b000: B<=8'b00000001;
        3'b001: B<=8'b00000010;
        3'b010: B<=8'b00000100;
        3'b011: B<=8'b00001000;
        3'b100: B<=8'b00010000;
        3'b101: B<=8'b00100000;
        3'b110: B<=8'b01000000;
        3'b111: B<=8'b10000000;
      endcase
      // $display($realtime," B=%b",B);
    end
  end
endmodule

module MEMORY(out,S);
  input [2:0]S;
  reg [7:0]mem [0:7];
  output reg [7:0] out;
  initial
    begin
      mem[0]=8'h01;
      mem[1]=8'h03;
      mem[2]=8'h07;
      mem[3]=8'h0F;
      mem[4]=8'h1F;
      mem[5]=8'h3F;
      mem[6]=8'h7F;
      mem[7]=8'hFF;
    end
  always@(S)
    begin
      case(S)
        3'd0:out<=mem[0];
        3'd1:out<=mem[1];
        3'd2:out<=mem[2];
        3'd3:out<=mem[3];
        3'd4:out<=mem[4];
        3'd5:out<=mem[5];
        3'd6:out<=mem[6];
        3'd7:out<=mem[7];
      endcase
    end
endmodule

module TOP_MODULE(out,clear,clk,en,S);
  output out;
  input clk,clear,en;
  input [2:0]S;
  wire [2:0] Q;
  wire [7:0]B,E,G;
  // always@*
    // $display(" Q=%b E=%b   out=%b",Q,E,out);
  COUNTER_3BIT counter(Q,clk,clear);
  DECODER d(B,Q,en);
  MEMORY m(G,S);
  MUX_ARRAY ma(E,B,G);
  MUX_8x1 out_mux(out,E,Q);
endmodule

module testbench;
  initial
  begin
    $dumpfile("CAtest.vcd");
    $dumpvars;
  end
  reg clk,clear,en;
  reg [2:0]S;
  wire out;
  TOP_MODULE t(out,clear,clk,1'b1,S);
  initial // to clear the counter
    begin
      clk=1'b0; S=3'b000; clear=1'b1;
      #1 clear=1'b0;
      #100 $finish;
    end
  always
      #0.5 clk=~clk;
  always
      #8 S=S+1;

  initial
      $monitor($time,"  , CLK = %b, S = %b, CLEAR = %b, O = %b", clk, S, clear, out);
endmodule

CAtest.vcd
$date
	Sat Nov 07 18:07:22 2020
$end
$version
	Icarus Verilog
$end
$timescale
	100us
$end
$scope module testbench $end
$var wire 1 ! out $end
$var reg 3 " S [2:0] $end
$var reg 1 # clear $end
$var reg 1 $ clk $end
$scope module t $end
$var wire 3 % S [2:0] $end
$var wire 1 # clear $end
$var wire 1 $ clk $end
$var wire 1 & en $end
$var wire 1 ! out $end
$var wire 3 ' Q [2:0] $end
$var wire 8 ( G [7:0] $end
$var wire 8 ) E [7:0] $end
$var wire 8 * B [7:0] $end
$scope module counter $end
$var wire 1 # clear $end
$var wire 1 $ clk $end
$var reg 3 + out [2:0] $end
$upscope $end
$scope module d $end
$var wire 3 , A [2:0] $end
$var wire 1 & EN $end
$var reg 8 - B [7:0] $end
$upscope $end
$scope module m $end
$var wire 3 . S [2:0] $end
$var reg 8 / out [7:0] $end
$upscope $end
$scope module ma $end
$var wire 8 0 B [7:0] $end
$var wire 8 1 F [7:0] $end
$var wire 8 2 E [7:0] $end
$scope begin mux_loop[0] $end
$scope module m $end
$var wire 2 3 in [1:0] $end
$var wire 1 4 sel $end
$var wire 1 5 out $end
$upscope $end
$upscope $end
$scope begin mux_loop[1] $end
$scope module m $end
$var wire 2 6 in [1:0] $end
$var wire 1 7 sel $end
$var wire 1 8 out $end
$upscope $end
$upscope $end
$scope begin mux_loop[2] $end
$scope module m $end
$var wire 2 9 in [1:0] $end
$var wire 1 : sel $end
$var wire 1 ; out $end
$upscope $end
$upscope $end
$scope begin mux_loop[3] $end
$scope module m $end
$var wire 2 < in [1:0] $end
$var wire 1 = sel $end
$var wire 1 > out $end
$upscope $end
$upscope $end
$scope begin mux_loop[4] $end
$scope module m $end
$var wire 2 ? in [1:0] $end
$var wire 1 @ sel $end
$var wire 1 A out $end
$upscope $end
$upscope $end
$scope begin mux_loop[5] $end
$scope module m $end
$var wire 2 B in [1:0] $end
$var wire 1 C sel $end
$var wire 1 D out $end
$upscope $end
$upscope $end
$scope begin mux_loop[6] $end
$scope module m $end
$var wire 2 E in [1:0] $end
$var wire 1 F sel $end
$var wire 1 G out $end
$upscope $end
$upscope $end
$scope begin mux_loop[7] $end
$scope module m $end
$var wire 2 H in [1:0] $end
$var wire 1 I sel $end
$var wire 1 J out $end
$upscope $end
$upscope $end
$upscope $end
$scope module out_mux $end
$var wire 8 K in [7:0] $end
$var wire 3 L sel [2:0] $end
$var wire 1 ! out $end
$upscope $end
$upscope $end
$upscope $end
$enddefinitions $end
#0
$dumpvars
b0 L
b1 K
0J
0I
b0 H
0G
0F
b0 E
0D
0C
b0 B
0A
0@
b0 ?
0>
0=
b0 <
0;
0:
b0 9
08
07
b0 6
15
14
b10 3
b1 2
b1 1
b1 0
b1 /
b0 .
b1 -
b0 ,
b0 +
b1 *
b1 )
b1 (
b0 '
1&
b0 %
0$
1#
b0 "
1!
$end
#5
b0 )
b0 2
b0 K
05
b0 3
b10 6
b10 *
b10 -
b10 0
0!
b1 '
b1 +
b1 ,
b1 L
1$
#10
0$
0#
#15
b0 6
b10 9
b100 *
b100 -
b100 0
b10 '
b10 +
b10 ,
b10 L
1$
#20
0$
#25
b0 9
b10 <
b1000 *
b1000 -
b1000 0
b11 '
b11 +
b11 ,
b11 L
1$
#30
0$
#35
b0 <
b10 ?
b10000 *
b10000 -
b10000 0
b100 '
b100 +
b100 ,
b100 L
1$
#40
0$
#45
b0 ?
b10 B
b100000 *
b100000 -
b100000 0
b101 '
b101 +
b101 ,
b101 L
1$
#50
0$
#55
b0 B
b10 E
b1000000 *
b1000000 -
b1000000 0
b110 '
b110 +
b110 ,
b110 L
1$
#60
0$
#65
b0 E
b10 H
b10000000 *
b10000000 -
b10000000 0
b111 '
b111 +
b111 ,
b111 L
1$
#70
0$
#75
1!
b1 )
b1 2
b1 K
15
b10 3
b0 H
b1 *
b1 -
b1 0
b0 '
b0 +
b0 ,
b0 L
1$
#80
17
b11 (
b11 /
b11 1
0$
b1 "
b1 %
b1 .
#85
05
b10 )
b10 2
b10 K
18
b0 3
b10 6
b10 *
b10 -
b10 0
1!
b1 '
b1 +
b1 ,
b1 L
1$
#90
0$
#95
b0 )
b0 2
b0 K
08
b0 6
b10 9
b100 *
b100 -
b100 0
0!
b10 '
b10 +
b10 ,
b10 L
1$
#100
0$
#105
b0 9
b10 <
b1000 *
b1000 -
b1000 0
b11 '
b11 +
b11 ,
b11 L
1$
#110
0$
#115
b0 <
b10 ?
b10000 *
b10000 -
b10000 0
b100 '
b100 +
b100 ,
b100 L
1$
#120
0$
#125
b0 ?
b10 B
b100000 *
b100000 -
b100000 0
b101 '
b101 +
b101 ,
b101 L
1$
#130
0$
#135
b0 B
b10 E
b1000000 *
b1000000 -
b1000000 0
b110 '
b110 +
b110 ,
b110 L
1$
#140
0$
#145
b0 E
b10 H
b10000000 *
b10000000 -
b10000000 0
b111 '
b111 +
b111 ,
b111 L
1$
#150
0$
#155
1!
b1 )
b1 2
b1 K
15
b10 3
b0 H
b1 *
b1 -
b1 0
b0 '
b0 +
b0 ,
b0 L
1$
#160
1:
b111 (
b111 /
b111 1
0$
b10 "
b10 %
b10 .
#165
05
b10 )
b10 2
b10 K
18
b0 3
b10 6
b10 *
b10 -
b10 0
1!
b1 '
b1 +
b1 ,
b1 L
1$
#170
0$
#175
08
b100 )
b100 2
b100 K
1;
b0 6
b10 9
b100 *
b100 -
b100 0
1!
b10 '
b10 +
b10 ,
b10 L
1$
#180
0$
#185
b0 )
b0 2
b0 K
0;
b0 9
b10 <
b1000 *
b1000 -
b1000 0
0!
b11 '
b11 +
b11 ,
b11 L
1$
#190
0$
#195
b0 <
b10 ?
b10000 *
b10000 -
b10000 0
b100 '
b100 +
b100 ,
b100 L
1$
#200
0$
#205
b0 ?
b10 B
b100000 *
b100000 -
b100000 0
b101 '
b101 +
b101 ,
b101 L
1$
#210
0$
#215
b0 B
b10 E
b1000000 *
b1000000 -
b1000000 0
b110 '
b110 +
b110 ,
b110 L
1$
#220
0$
#225
b0 E
b10 H
b10000000 *
b10000000 -
b10000000 0
b111 '
b111 +
b111 ,
b111 L
1$
#230
0$
#235
1!
b1 )
b1 2
b1 K
15
b10 3
b0 H
b1 *
b1 -
b1 0
b0 '
b0 +
b0 ,
b0 L
1$
#240
1=
b1111 (
b1111 /
b1111 1
0$
b11 "
b11 %
b11 .
#245
05
b10 )
b10 2
b10 K
18
b0 3
b10 6
b10 *
b10 -
b10 0
1!
b1 '
b1 +
b1 ,
b1 L
1$
#250
0$
#255
08
b100 )
b100 2
b100 K
1;
b0 6
b10 9
b100 *
b100 -
b100 0
1!
b10 '
b10 +
b10 ,
b10 L
1$
#260
0$
#265
0;
b1000 )
b1000 2
b1000 K
1>
b0 9
b10 <
b1000 *
b1000 -
b1000 0
1!
b11 '
b11 +
b11 ,
b11 L
1$
#270
0$
#275
b0 )
b0 2
b0 K
0>
b0 <
b10 ?
b10000 *
b10000 -
b10000 0
0!
b100 '
b100 +
b100 ,
b100 L
1$
#280
0$
#285
b0 ?
b10 B
b100000 *
b100000 -
b100000 0
b101 '
b101 +
b101 ,
b101 L
1$
#290
0$
#295
b0 B
b10 E
b1000000 *
b1000000 -
b1000000 0
b110 '
b110 +
b110 ,
b110 L
1$
#300
0$
#305
b0 E
b10 H
b10000000 *
b10000000 -
b10000000 0
b111 '
b111 +
b111 ,
b111 L
1$
#310
0$
#315
1!
b1 )
b1 2
b1 K
15
b10 3
b0 H
b1 *
b1 -
b1 0
b0 '
b0 +
b0 ,
b0 L
1$
#320
1@
b11111 (
b11111 /
b11111 1
0$
b100 "
b100 %
b100 .
#325
05
b10 )
b10 2
b10 K
18
b0 3
b10 6
b10 *
b10 -
b10 0
1!
b1 '
b1 +
b1 ,
b1 L
1$
#330
0$
#335
08
b100 )
b100 2
b100 K
1;
b0 6
b10 9
b100 *
b100 -
b100 0
1!
b10 '
b10 +
b10 ,
b10 L
1$
#340
0$
#345
0;
b1000 )
b1000 2
b1000 K
1>
b0 9
b10 <
b1000 *
b1000 -
b1000 0
1!
b11 '
b11 +
b11 ,
b11 L
1$
#350
0$
#355
0>
b10000 )
b10000 2
b10000 K
1A
b0 <
b10 ?
b10000 *
b10000 -
b10000 0
1!
b100 '
b100 +
b100 ,
b100 L
1$
#360
0$
#365
b0 )
b0 2
b0 K
0A
b0 ?
b10 B
b100000 *
b100000 -
b100000 0
0!
b101 '
b101 +
b101 ,
b101 L
1$
#370
0$
#375
b0 B
b10 E
b1000000 *
b1000000 -
b1000000 0
b110 '
b110 +
b110 ,
b110 L
1$
#380
0$
#385
b0 E
b10 H
b10000000 *
b10000000 -
b10000000 0
b111 '
b111 +
b111 ,
b111 L
1$
#390
0$
#395
1!
b1 )
b1 2
b1 K
15
b10 3
b0 H
b1 *
b1 -
b1 0
b0 '
b0 +
b0 ,
b0 L
1$
#400
1C
b111111 (
b111111 /
b111111 1
0$
b101 "
b101 %
b101 .
#405
05
b10 )
b10 2
b10 K
18
b0 3
b10 6
b10 *
b10 -
b10 0
1!
b1 '
b1 +
b1 ,
b1 L
1$
#410
0$
#415
08
b100 )
b100 2
b100 K
1;
b0 6
b10 9
b100 *
b100 -
b100 0
1!
b10 '
b10 +
b10 ,
b10 L
1$
#420
0$
#425
0;
b1000 )
b1000 2
b1000 K
1>
b0 9
b10 <
b1000 *
b1000 -
b1000 0
1!
b11 '
b11 +
b11 ,
b11 L
1$
#430
0$
#435
0>
b10000 )
b10000 2
b10000 K
1A
b0 <
b10 ?
b10000 *
b10000 -
b10000 0
1!
b100 '
b100 +
b100 ,
b100 L
1$
#440
0$
#445
0A
b100000 )
b100000 2
b100000 K
1D
b0 ?
b10 B
b100000 *
b100000 -
b100000 0
1!
b101 '
b101 +
b101 ,
b101 L
1$
#450
0$
#455
b0 )
b0 2
b0 K
0D
b0 B
b10 E
b1000000 *
b1000000 -
b1000000 0
0!
b110 '
b110 +
b110 ,
b110 L
1$
#460
0$
#465
b0 E
b10 H
b10000000 *
b10000000 -
b10000000 0
b111 '
b111 +
b111 ,
b111 L
1$
#470
0$
#475
1!
b1 )
b1 2
b1 K
15
b10 3
b0 H
b1 *
b1 -
b1 0
b0 '
b0 +
b0 ,
b0 L
1$
#480
1F
b1111111 (
b1111111 /
b1111111 1
0$
b110 "
b110 %
b110 .
#485
05
b10 )
b10 2
b10 K
18
b0 3
b10 6
b10 *
b10 -
b10 0
1!
b1 '
b1 +
b1 ,
b1 L
1$
#490
0$
#495
08
b100 )
b100 2
b100 K
1;
b0 6
b10 9
b100 *
b100 -
b100 0
1!
b10 '
b10 +
b10 ,
b10 L
1$
#500
0$
#505
0;
b1000 )
b1000 2
b1000 K
1>
b0 9
b10 <
b1000 *
b1000 -
b1000 0
1!
b11 '
b11 +
b11 ,
b11 L
1$
#510
0$
#515
0>
b10000 )
b10000 2
b10000 K
1A
b0 <
b10 ?
b10000 *
b10000 -
b10000 0
1!
b100 '
b100 +
b100 ,
b100 L
1$
#520
0$
#525
0A
b100000 )
b100000 2
b100000 K
1D
b0 ?
b10 B
b100000 *
b100000 -
b100000 0
1!
b101 '
b101 +
b101 ,
b101 L
1$
#530
0$
#535
0D
b1000000 )
b1000000 2
b1000000 K
1G
b0 B
b10 E
b1000000 *
b1000000 -
b1000000 0
1!
b110 '
b110 +
b110 ,
b110 L
1$
#540
0$
#545
b0 )
b0 2
b0 K
0G
b0 E
b10 H
b10000000 *
b10000000 -
b10000000 0
0!
b111 '
b111 +
b111 ,
b111 L
1$
#550
0$
#555
1!
b1 )
b1 2
b1 K
15
b10 3
b0 H
b1 *
b1 -
b1 0
b0 '
b0 +
b0 ,
b0 L
1$
#560
1I
b11111111 (
b11111111 /
b11111111 1
0$
b111 "
b111 %
b111 .
#565
05
b10 )
b10 2
b10 K
18
b0 3
b10 6
b10 *
b10 -
b10 0
1!
b1 '
b1 +
b1 ,
b1 L
1$
#570
0$
#575
08
b100 )
b100 2
b100 K
1;
b0 6
b10 9
b100 *
b100 -
b100 0
1!
b10 '
b10 +
b10 ,
b10 L
1$
#580
0$
#585
0;
b1000 )
b1000 2
b1000 K
1>
b0 9
b10 <
b1000 *
b1000 -
b1000 0
1!
b11 '
b11 +
b11 ,
b11 L
1$
#590
0$
#595
0>
b10000 )
b10000 2
b10000 K
1A
b0 <
b10 ?
b10000 *
b10000 -
b10000 0
1!
b100 '
b100 +
b100 ,
b100 L
1$
#600
0$
#605
0A
b100000 )
b100000 2
b100000 K
1D
b0 ?
b10 B
b100000 *
b100000 -
b100000 0
1!
b101 '
b101 +
b101 ,
b101 L
1$
#610
0$
#615
0D
b1000000 )
b1000000 2
b1000000 K
1G
b0 B
b10 E
b1000000 *
b1000000 -
b1000000 0
1!
b110 '
b110 +
b110 ,
b110 L
1$
#620
0$
#625
0G
b10000000 )
b10000000 2
b10000000 K
1J
b0 E
b10 H
b10000000 *
b10000000 -
b10000000 0
1!
b111 '
b111 +
b111 ,
b111 L
1$
#630
0$
#635
15
b1 )
b1 2
b1 K
0J
b10 3
b0 H
b1 *
b1 -
b1 0
1!
b0 '
b0 +
b0 ,
b0 L
1$
#640
07
0:
0=
0@
0C
0F
0I
b1 (
b1 /
b1 1
0$
b0 "
b0 %
b0 .
#645
b0 )
b0 2
b0 K
05
b0 3
b10 6
b10 *
b10 -
b10 0
0!
b1 '
b1 +
b1 ,
b1 L
1$
#650
0$
#655
b0 6
b10 9
b100 *
b100 -
b100 0
b10 '
b10 +
b10 ,
b10 L
1$
#660
0$
#665
b0 9
b10 <
b1000 *
b1000 -
b1000 0
b11 '
b11 +
b11 ,
b11 L
1$
#670
0$
#675
b0 <
b10 ?
b10000 *
b10000 -
b10000 0
b100 '
b100 +
b100 ,
b100 L
1$
#680
0$
#685
b0 ?
b10 B
b100000 *
b100000 -
b100000 0
b101 '
b101 +
b101 ,
b101 L
1$
#690
0$
#695
b0 B
b10 E
b1000000 *
b1000000 -
b1000000 0
b110 '
b110 +
b110 ,
b110 L
1$
#700
0$
#705
b0 E
b10 H
b10000000 *
b10000000 -
b10000000 0
b111 '
b111 +
b111 ,
b111 L
1$
#710
0$
#715
1!
b1 )
b1 2
b1 K
15
b10 3
b0 H
b1 *
b1 -
b1 0
b0 '
b0 +
b0 ,
b0 L
1$
#720
17
b11 (
b11 /
b11 1
0$
b1 "
b1 %
b1 .
#725
05
b10 )
b10 2
b10 K
18
b0 3
b10 6
b10 *
b10 -
b10 0
1!
b1 '
b1 +
b1 ,
b1 L
1$
#730
0$
#735
b0 )
b0 2
b0 K
08
b0 6
b10 9
b100 *
b100 -
b100 0
0!
b10 '
b10 +
b10 ,
b10 L
1$
#740
0$
#745
b0 9
b10 <
b1000 *
b1000 -
b1000 0
b11 '
b11 +
b11 ,
b11 L
1$
#750
0$
#755
b0 <
b10 ?
b10000 *
b10000 -
b10000 0
b100 '
b100 +
b100 ,
b100 L
1$
#760
0$
#765
b0 ?
b10 B
b100000 *
b100000 -
b100000 0
b101 '
b101 +
b101 ,
b101 L
1$
#770
0$
#775
b0 B
b10 E
b1000000 *
b1000000 -
b1000000 0
b110 '
b110 +
b110 ,
b110 L
1$
#780
0$
#785
b0 E
b10 H
b10000000 *
b10000000 -
b10000000 0
b111 '
b111 +
b111 ,
b111 L
1$
#790
0$
#795
1!
b1 )
b1 2
b1 K
15
b10 3
b0 H
b1 *
b1 -
b1 0
b0 '
b0 +
b0 ,
b0 L
1$
#800
1:
b111 (
b111 /
b111 1
0$
b10 "
b10 %
b10 .
#805
05
b10 )
b10 2
b10 K
18
b0 3
b10 6
b10 *
b10 -
b10 0
1!
b1 '
b1 +
b1 ,
b1 L
1$
#810
0$
#815
08
b100 )
b100 2
b100 K
1;
b0 6
b10 9
b100 *
b100 -
b100 0
1!
b10 '
b10 +
b10 ,
b10 L
1$
#820
0$
#825
b0 )
b0 2
b0 K
0;
b0 9
b10 <
b1000 *
b1000 -
b1000 0
0!
b11 '
b11 +
b11 ,
b11 L
1$
#830
0$
#835
b0 <
b10 ?
b10000 *
b10000 -
b10000 0
b100 '
b100 +
b100 ,
b100 L
1$
#840
0$
#845
b0 ?
b10 B
b100000 *
b100000 -
b100000 0
b101 '
b101 +
b101 ,
b101 L
1$
#850
0$
#855
b0 B
b10 E
b1000000 *
b1000000 -
b1000000 0
b110 '
b110 +
b110 ,
b110 L
1$
#860
0$
#865
b0 E
b10 H
b10000000 *
b10000000 -
b10000000 0
b111 '
b111 +
b111 ,
b111 L
1$
#870
0$
#875
1!
b1 )
b1 2
b1 K
15
b10 3
b0 H
b1 *
b1 -
b1 0
b0 '
b0 +
b0 ,
b0 L
1$
#880
1=
b1111 (
b1111 /
b1111 1
0$
b11 "
b11 %
b11 .
#885
05
b10 )
b10 2
b10 K
18
b0 3
b10 6
b10 *
b10 -
b10 0
1!
b1 '
b1 +
b1 ,
b1 L
1$
#890
0$
#895
08
b100 )
b100 2
b100 K
1;
b0 6
b10 9
b100 *
b100 -
b100 0
1!
b10 '
b10 +
b10 ,
b10 L
1$
#900
0$
#905
0;
b1000 )
b1000 2
b1000 K
1>
b0 9
b10 <
b1000 *
b1000 -
b1000 0
1!
b11 '
b11 +
b11 ,
b11 L
1$
#910
0$
#915
b0 )
b0 2
b0 K
0>
b0 <
b10 ?
b10000 *
b10000 -
b10000 0
0!
b100 '
b100 +
b100 ,
b100 L
1$
#920
0$
#925
b0 ?
b10 B
b100000 *
b100000 -
b100000 0
b101 '
b101 +
b101 ,
b101 L
1$
#930
0$
#935
b0 B
b10 E
b1000000 *
b1000000 -
b1000000 0
b110 '
b110 +
b110 ,
b110 L
1$
#940
0$
#945
b0 E
b10 H
b10000000 *
b10000000 -
b10000000 0
b111 '
b111 +
b111 ,
b111 L
1$
#950
0$
#955
1!
b1 )
b1 2
b1 K
15
b10 3
b0 H
b1 *
b1 -
b1 0
b0 '
b0 +
b0 ,
b0 L
1$
#960
1@
b11111 (
b11111 /
b11111 1
0$
b100 "
b100 %
b100 .
#965
05
b10 )
b10 2
b10 K
18
b0 3
b10 6
b10 *
b10 -
b10 0
1!
b1 '
b1 +
b1 ,
b1 L
1$
#970
0$
#975
08
b100 )
b100 2
b100 K
1;
b0 6
b10 9
b100 *
b100 -
b100 0
1!
b10 '
b10 +
b10 ,
b10 L
1$
#980
0$
#985
0;
b1000 )
b1000 2
b1000 K
1>
b0 9
b10 <
b1000 *
b1000 -
b1000 0
1!
b11 '
b11 +
b11 ,
b11 L
1$
#990
0$
#995
0>
b10000 )
b10000 2
b10000 K
1A
b0 <
b10 ?
b10000 *
b10000 -
b10000 0
1!
b100 '
b100 +
b100 ,
b100 L
1$
#1000
0$
#1005
b0 )
b0 2
b0 K
0A
b0 ?
b10 B
b100000 *
b100000 -
b100000 0
0!
b101 '
b101 +
b101 ,
b101 L
1$
